advanced_computation/__init__.py
advanced_computation/anomaly_detection.py
advanced_computation/bayesian_analysis.py
advanced_computation/emd.py
advanced_computation/generative_signal_synthesis.py
advanced_computation/harmonic_percussive_separation.py
advanced_computation/kalman_filter.py
advanced_computation/multimodal_fusion.py
advanced_computation/neural_network_filtering.py
advanced_computation/non_linear_analysis.py
advanced_computation/pitch_shift.py
advanced_computation/real_time_anomaly_detection.py
advanced_computation/reinforcement_learning_filter.py
advanced_computation/sparse_signal_processing.py
filtering/__init__.py
filtering/advanced_signal_filtering.py
filtering/artifact_removal.py
filtering/signal_filtering.py
filtering/signal_quality.py
filtering/signal_quality_index.py
respiratory_analysis/__init__.py
respiratory_analysis/estimate_rr/__init__.py
respiratory_analysis/estimate_rr/fft_based_rr.py
respiratory_analysis/estimate_rr/frequency_domain_rr.py
respiratory_analysis/estimate_rr/peak_detection_rr.py
respiratory_analysis/estimate_rr/time_domain_rr.py
respiratory_analysis/fusion/__init__.py
respiratory_analysis/fusion/multimodal_analysis.py
respiratory_analysis/fusion/ppg_ecg_fusion.py
respiratory_analysis/fusion/respiratory_cardiac_fusion.py
respiratory_analysis/preprocess/__init__.py
respiratory_analysis/preprocess/noise_reduction.py
respiratory_analysis/preprocess/preprocess.py
respiratory_analysis/sleep_apnea_detection/__init__.py
respiratory_analysis/sleep_apnea_detection/amplitude_threshold.py
respiratory_analysis/sleep_apnea_detection/pause_detection.py
time_domain/__init__.py
time_domain/cross_signal_analysis.py
time_domain/ensemble_based_feature_extraction.py
time_domain/envelope_detection.py
time_domain/peak_detection.py
time_domain/signal_change_detection.py
time_domain/signal_power_analysis.py
time_domain/signal_segmentation.py
time_domain/trend_analysis.py
transforms/__init__.py
transforms/chroma_stft.py
vital_DSP-0.1.1rc1.dist-info/LICENSE
vital_DSP-0.1.1rc1.dist-info/METADATA
vital_DSP-0.1.1rc1.dist-info/WHEEL
vital_DSP-0.1.1rc1.dist-info/top_level.txt
vital_DSP-0.1.1rc1.dist-info/RECORD
