Metadata-Version: 2.1
Name: vital-DSP
Version: 0.1.1rc1
Summary: A comprehensive toolkit for Digital Signal Processing in healthcare applications.
Home-page: https://github.com/Oucru-Innovations/vital-DSP
Author: van-koha
Author-email: vital.data@oucru.org
License: MIT
Classifier: Programming Language :: Python :: 3
Classifier: License :: OSI Approved :: MIT License
Classifier: Operating System :: OS Independent
Classifier: Development Status :: 4 - Beta
Classifier: Intended Audience :: Developers
Classifier: Topic :: Software Development :: Libraries :: Python Modules
Classifier: Topic :: Scientific/Engineering :: Medical Science Apps.
Requires-Python: >=3.9
License-File: LICENSE
Requires-Dist: numpy >=1.19.2
Requires-Dist: scipy >=1.5.2
Requires-Dist: plotly >=4.14.3
Requires-Dist: pywt >=1.0.10
Requires-Dist: scikit-learn >=0.23.2
